mkdocs_ansible/__init__.py
mkdocs_ansible/_version.py
mkdocs_ansible/main.html
mkdocs_ansible/mkdocs_theme.yml
mkdocs_ansible/.icons/logo.svg
mkdocs_ansible/assets/images/favicon.ico
mkdocs_ansible/assets/images/logo.png
mkdocs_ansible/assets/images/logo.svg
mkdocs_ansible/assets/stylesheets/ansible.css
mkdocs_ansible-25.6.0.dist-info/METADATA
mkdocs_ansible-25.6.0.dist-info/WHEEL
mkdocs_ansible-25.6.0.dist-info/entry_points.txt
mkdocs_ansible-25.6.0.dist-info/top_level.txt
mkdocs_ansible-25.6.0.dist-info/RECORD
